realtime/__init__.py
realtime/_async/__init__.py
realtime/_async/channel.py
realtime/_async/client.py
realtime/_async/presence.py
realtime/_async/push.py
realtime/_async/timer.py
realtime/_sync/__init__.py
realtime/_sync/channel.py
realtime/_sync/client.py
realtime/_sync/presence.py
realtime/exceptions.py
realtime/message.py
realtime/py.typed
realtime/transformers.py
realtime/types.py
realtime/utils.py
realtime/version.py
realtime-2.23.1.dist-info/METADATA
realtime-2.23.1.dist-info/WHEEL
realtime-2.23.1.dist-info/RECORD
