Metadata-Version: 2.4
Name: realtime
Version: 2.23.1
Summary: 
License-Expression: MIT
Author: Joel Lee
Author-email: joel@joellee.org
Maintainer: Leonardo Santiago
Maintainer-email: leonardo.santiago@supabase.io
Requires-Python: >=3.9
Classifier: Programming Language :: Python :: 3
Classifier: Programming Language :: Python :: 3.9
Classifier: Programming Language :: Python :: 3.10
Classifier: Programming Language :: Python :: 3.11
Classifier: Programming Language :: Python :: 3.12
Classifier: Programming Language :: Python :: 3.13
Classifier: Programming Language :: Python :: 3.14
Requires-Dist: pydantic (>=2.11.7,<3.0.0)
Requires-Dist: typing-extensions (>=4.14.0)
Requires-Dist: websockets (>=11,<16)
Project-URL: Documentation, https://github.com/supabase/supabase/tree/main/src/realime
Project-URL: Homepage, https://github.com/supabase/supabase/tree/main/src/realime
Project-URL: Repository, https://github.com/supabase/supabase-py
Project-URL: changelog, https://github.com/supabase/supabase-py/tree/main/CHANGELOG.md
